ivrc2country/__init__.py
tests/__init__.py
tests/test_lists.py
tests/test_lookup.py
ivrc2country-0.1.2.dist-info/LICENSE
ivrc2country-0.1.2.dist-info/METADATA
ivrc2country-0.1.2.dist-info/WHEEL
ivrc2country-0.1.2.dist-info/top_level.txt
ivrc2country-0.1.2.dist-info/RECORD
