Metadata-Version: 2.1
Name: ivrc2country
Version: 0.1.2
Summary: Converts international vehicle license codes to 3-letter ISO3166-1 alpha-3 country codes
Home-page: https://github.com/tuergeist/ivrc2country
Author: Christoph Becker
Author-email: tuergeist@gmail.com
License: UNKNOWN
Platform: UNKNOWN
Classifier: Programming Language :: Python :: 3
Classifier: License :: OSI Approved :: MIT License
Classifier: Operating System :: OS Independent
